bloggerkit/__init__.py
bloggerkit/client.py
bloggerkit/model.py
bloggerkit-0.7.0.dist-info/METADATA
bloggerkit-0.7.0.dist-info/WHEEL
bloggerkit-0.7.0.dist-info/top_level.txt
bloggerkit-0.7.0.dist-info/RECORD
