Metadata-Version: 2.4
Name: bloggerkit
Version: 0.7.0
Summary: A toolkit for interacting with the Google Blogger API
Home-page: https://github.com/StatPan/bloggerkit
Author: StatPan Lab
Author-email: statpan@naver.com
Project-URL: Homepage, https://github.com/StatPan/bloggerkit
Requires-Python: >=3.10
Requires-Dist: google-api-python-client>=2.165.0
Requires-Dist: google-auth-oauthlib>=1.2.1
Requires-Dist: setuptools>=77.0.3
Dynamic: author
Dynamic: author-email
Dynamic: home-page
